{
	"geometry.axolotl": {
		"texturewidth": 80,
		"textureheight": 80,
		"visible_bounds_width": 2,
		"visible_bounds_height": 1,
		"visible_bounds_offset": [
			0,
			0.5,
			0
		],
		"bones": [
			{
				"name": "body",
				"pivot": [
					0,
					3.5,
					3
				],
				"cubes": [
					{
						"origin": [
							-2,
							0,
							-8
						],
						"size": [
							4,
							3,
							13
						],
						"uv": [
							40,
							0
						]
					},
					{
						"origin": [
							-3,
							-1,
							-8
						],
						"size": [
							6,
							5,
							14
						],
						"uv": [
							0,
							0
						]
					}
				]
			},
			{
				"name": "tail_a",
				"parent": "body",
				"pivot": [
					0,
					1,
					5
				],
				"cubes": [
					{
						"origin": [
							-1,
							0,
							5
						],
						"size": [
							2,
							2,
							6
						],
						"uv": [
							36,
							38
						]
					},
					{
						"origin": [
							-2,
							-1,
							5
						],
						"size": [
							4,
							4,
							6
						],
						"uv": [
							28,
							19
						]
					}
				]
			},
			{
				"name": "tail_b",
				"parent": "body",
				"pivot": [
					0,
					0.5,
					10.125
				],
				"cubes": [
					{
						"origin": [
							-1,
							0,
							11
						],
						"size": [
							2,
							1,
							4
						],
						"uv": [
							14,
							46
						]
					},
					{
						"origin": [
							0,
							-1,
							12
						],
						"size": [
							0,
							3,
							4
						],
						"uv": [
							0,
							51
						]
					},
					{
						"origin": [
							0,
							0,
							16
						],
						"size": [
							0,
							1,
							1
						],
						"uv": [
							18,
							54
						]
					},
					{
						"origin": [
							-2,
							-1,
							11
						],
						"size": [
							4,
							3,
							4
						],
						"uv": [
							52,
							38
						]
					}
				]
			},
			{
				"name": "leg_b",
				"pivot": [
					1.5,
					2.5,
					2
				],
				"cubes": [
					{
						"origin": [
							1.51567,
							0.07943,
							0.78668
						],
						"size": [
							5,
							1,
							2
						],
						"uv": [
							54,
							46
						]
					},
					{
						"origin": [
							1.51567,
							-0.92057,
							-0.21332
						],
						"size": [
							6,
							3,
							4
						],
						"uv": [
							42,
							31
						]
					}
				]
			},
			{
				"name": "leg_c",
				"pivot": [
					-1.5,
					0.57943,
					-5.78668
				],
				"cubes": [
					{
						"origin": [
							-6.48433,
							0.07943,
							-6.78668
						],
						"size": [
							5,
							1,
							2
						],
						"uv": [
							40,
							46
						]
					},
					{
						"origin": [
							-6.48433,
							-0.92057,
							-7.78668
						],
						"size": [
							5,
							3,
							4
						],
						"uv": [
							18,
							38
						]
					}
				]
			},
			{
				"name": "leg_d",
				"pivot": [
					-1.5,
					0.57943,
					1.78668
				],
				"cubes": [
					{
						"origin": [
							-6.48433,
							0.07943,
							0.78668
						],
						"size": [
							5,
							1,
							2
						],
						"uv": [
							26,
							46
						]
					},
					{
						"origin": [
							-6.48433,
							-0.92057,
							-0.21332
						],
						"size": [
							5,
							3,
							4
						],
						"uv": [
							0,
							38
						]
					}
				]
			},
			{
				"name": "leg_a",
				"pivot": [
					1.5,
					2.5,
					-6
				],
				"cubes": [
					{
						"origin": [
							1.51567,
							0.07943,
							-6.78668
						],
						"size": [
							5,
							1,
							2
						],
						"uv": [
							0,
							46
						]
					},
					{
						"origin": [
							1.51567,
							-0.92057,
							-7.78668
						],
						"size": [
							6,
							3,
							4
						],
						"uv": [
							22,
							31
						]
					}
				]
			},
			{
				"name": "head",
				"pivot": [
					0,
					2,
					-8
				],
				"cubes": [
					{
						"origin": [
							-3,
							1,
							-13
						],
						"size": [
							6,
							3,
							5
						],
						"uv": [
							48,
							19
						]
					},
					{
						"origin": [
							3,
							2,
							-9
						],
						"size": [
							4,
							1,
							0
						],
						"uv": [
							8,
							51
						]
					},
					{
						"origin": [
							-7,
							2,
							-9
						],
						"size": [
							4,
							1,
							0
						],
						"uv": [
							8,
							52
						]
					},
					{
						"origin": [
							3,
							2,
							-11
						],
						"size": [
							4,
							1,
							0
						],
						"uv": [
							8,
							53
						]
					},
					{
						"origin": [
							-7,
							2,
							-11
						],
						"size": [
							4,
							1,
							0
						],
						"uv": [
							8,
							54
						]
					},
					{
						"origin": [
							-6,
							1,
							-11
						],
						"size": [
							1,
							3,
							0
						],
						"uv": [
							16,
							54
						]
					},
					{
						"origin": [
							-5,
							1,
							-9
						],
						"size": [
							1,
							3,
							0
						],
						"uv": [
							16,
							51
						]
					},
					{
						"origin": [
							5,
							1,
							-11
						],
						"size": [
							1,
							3,
							0
						],
						"uv": [
							8,
							55
						]
					},
					{
						"origin": [
							4,
							1,
							-9
						],
						"size": [
							1,
							3,
							0
						],
						"uv": [
							18,
							51
						]
					},
					{
						"origin": [
							-4,
							-1,
							-14
						],
						"size": [
							8,
							6,
							6
						],
						"uv": [
							0,
							19
						]
					},
					{
						"origin": [
							-3,
							0,
							-13
						],
						"size": [
							6,
							1,
							5
						],
						"uv": [
							0,
							31
						]
					}
				]
			}
		]
	}
}